pharia_inference_sdk/__init__.py
pharia_inference_sdk/py.typed
pharia_inference_sdk/connectors/__init__.py
pharia_inference_sdk/connectors/limited_concurrency_client.py
pharia_inference_sdk/core/__init__.py
pharia_inference_sdk/core/chunk.py
pharia_inference_sdk/core/detect_language.py
pharia_inference_sdk/core/echo.py
pharia_inference_sdk/core/instruct.py
pharia_inference_sdk/core/model.py
pharia_inference_sdk/core/prompt_template.py
pharia_inference_sdk/core/task.py
pharia_inference_sdk/core/text_highlight.py
pharia_inference_sdk/core/tracer/__init__.py
pharia_inference_sdk/core/tracer/composite_tracer.py
pharia_inference_sdk/core/tracer/file_tracer.py
pharia_inference_sdk/core/tracer/in_memory_tracer.py
pharia_inference_sdk/core/tracer/open_telemetry_tracer.py
pharia_inference_sdk/core/tracer/persistent_tracer.py
pharia_inference_sdk/core/tracer/tracer.py
pharia_inference_sdk-0.1.6.dist-info/METADATA
pharia_inference_sdk-0.1.6.dist-info/WHEEL
pharia_inference_sdk-0.1.6.dist-info/licenses/LICENSE
pharia_inference_sdk-0.1.6.dist-info/licenses/NOTICE.md
pharia_inference_sdk-0.1.6.dist-info/RECORD
