Metadata-Version: 2.4
Name: pharia-inference-sdk
Version: 0.1.6
Project-URL: repository, https://github.com/Aleph-Alpha/pharia-inference-sdk.git
Author-email: Aleph Alpha Engineering <engineering@aleph-alpha.com>
License-File: LICENSE
License-File: NOTICE.md
Requires-Python: <3.13,>=3.10
Requires-Dist: aleph-alpha-client<11.0.0,>=10.2.2
Requires-Dist: ipykernel<7,>=6.29.5
Requires-Dist: lingua-language-detector>=2.0.0
Requires-Dist: opentelemetry-api<2,>=1.29.0
Requires-Dist: opentelemetry-exporter-otlp-proto-http==1.34.1
Requires-Dist: opentelemetry-sdk<2,>=1.29.0
Requires-Dist: pycountry<25,>=24.6.1
Requires-Dist: pydantic>=2.0.0
Requires-Dist: python-liquid==1.9.4
Requires-Dist: rich<15,>=14.0.0
Requires-Dist: semantic-text-splitter>=0.5.0
